<?xml version="1.0" encoding="utf-8" ?>
<dwsync>
<file name="dynamic_custom_field.js.php" server="nichebill.com/public_html/" local="128057620860000000" remote="128909152800000000" />
<file name="httpclient.js" server="nichebill.com/public_html/" local="128057620920000000" remote="128909152800000000" />
<file name="autocomplete.js" server="nichebill.com/public_html/" local="128057620840000000" remote="128909152800000000" />
<file name="browserSniffer.js" server="nichebill.com/public_html/" local="128057620840000000" remote="128909152800000000" />
<file name="dtree.js" server="nichebill.com/public_html/" local="128057620860000000" remote="128909152800000000" />
<file name="dynCalendar.js" server="nichebill.com/public_html/" local="128057620880000000" remote="128909152800000000" />
<file name="expandable_cell.js" server="nichebill.com/public_html/" local="128057620900000000" remote="128909152800000000" />
<file name="global.js" server="nichebill.com/public_html/" local="128057620920000000" remote="128909152800000000" />
<file name="overlib.js" server="nichebill.com/public_html/" local="128057620960000000" remote="128909152800000000" />
<file name="overlib_mini.js" server="nichebill.com/public_html/" local="128057620960000000" remote="128909152800000000" />
<file name="post_load.js" server="nichebill.com/public_html/" local="128057620980000000" remote="128909152800000000" />
<file name="validation.js" server="nichebill.com/public_html/" local="128057620980000000" remote="128909152800000000" />
</dwsync>